dataverse_utils/__init__.py
dataverse_utils/collections.py
dataverse_utils/data/LDC_EULA_general.md
dataverse_utils/dataverse_utils.py
dataverse_utils/dvdata.py
dataverse_utils/ldc.py
dataverse_utils/scripts/dv_collection_info.py
dataverse_utils/scripts/dv_del.py
dataverse_utils/scripts/dv_ldc_uploader.py
dataverse_utils/scripts/dv_list_files.py
dataverse_utils/scripts/dv_manifest_gen.py
dataverse_utils/scripts/dv_pg_facet_date.py
dataverse_utils/scripts/dv_readme_creator.py
dataverse_utils/scripts/dv_record_copy.py
dataverse_utils/scripts/dv_release.py
dataverse_utils/scripts/dv_replace_licence.py
dataverse_utils/scripts/dv_study_migrator.py
dataverse_utils/scripts/dv_upload_tsv.py
dataverse_utils-0.21.5.dist-info/LICENCE.md
dataverse_utils-0.21.5.dist-info/METADATA
dataverse_utils-0.21.5.dist-info/WHEEL
dataverse_utils-0.21.5.dist-info/entry_points.txt
dataverse_utils-0.21.5.dist-info/RECORD
