Metadata-Version: 2.3
Name: dataverse-utils
Version: 0.21.5
Summary: Utilities for the Dataverse data respository system
License: MIT
Keywords: Harvard Dataverse,Dataverse,research data management,data repository
Author: Paul Lesack
Author-email: paul.lesack@ubc.ca
Requires-Python: >=3.10, <4.0
Classifier: License :: OSI Approved :: MIT License
Classifier: Programming Language :: Python :: 3
Classifier: Programming Language :: Python :: 3.10
Classifier: Programming Language :: Python :: 3.11
Classifier: Programming Language :: Python :: 3.12
Classifier: Programming Language :: Python :: 3.13
Requires-Dist: beautifulsoup4 (>=4.12.2)
Requires-Dist: certifi (>=2022.12.7)
Requires-Dist: chardet (>=5.1.0)
Requires-Dist: charset-normalizer (>=3.1.0)
Requires-Dist: dryad2dataverse (>=0.6.1)
Requires-Dist: idna (>=3.4)
Requires-Dist: markdown (>=3.2.1)
Requires-Dist: markdown-pdf (>=1.9,<2.0)
Requires-Dist: markdownify (>=0.11.6)
Requires-Dist: pyreadr (>=0.5.3,<0.6.0)
Requires-Dist: pyreadstat (>=1.3.1,<2.0.0)
Requires-Dist: requests (>=2.29.0)
Requires-Dist: requests-toolbelt (>=1.0.0)
Requires-Dist: six (>=1.16.0)
Requires-Dist: soupsieve (>=2.4.1)
Requires-Dist: tqdm (>=4.67.1,<5.0.0)
Requires-Dist: urllib3 (>=2.6.1)
Project-URL: Homepage, https://ubc-library-rc.github.io/dataverse_utils
Project-URL: Issue Tracker, https://github.com/ubc-library-rc/dataverse_utils/issues
Project-URL: Repository, https://github.com/ubc-library-rc/dataverse_utils.git
